LICENSE.txt
MANIFEST.in
README.rst
setup.py
docs/changes.rst
nester_pre/__init__.py
nester_pre/nester_pre.py
nester_pre/nester_pre_version.py
nester_pre.egg-info/PKG-INFO
nester_pre.egg-info/SOURCES.txt
nester_pre.egg-info/dependency_links.txt
nester_pre.egg-info/top_level.txt
tests/printOut.py