Metadata-Version: 1.1
Name: nester-pre
Version: 1.4.4
Summary: nester_pre let you print nestered data. i.e. nested list
Home-page: https://github.com/immark/nester_pre
Author: Mark Ma
Author-email: maanyng@yahoo.com.tw
License: MIT
Platform: any
Classifier: Environment :: Console
Classifier: Intended Audience :: Developers
Classifier: License :: OSI Approved :: MIT License
Classifier: Operating System :: OS Independent
Classifier: Programming Language :: Python
Classifier: Topic :: Utilities
Classifier: Topic :: Software Development :: Libraries :: Python Modules
